{"title":"اختراع (دويتو)","lyrics":"(تامر حسني)\nمعروف أنا من زمان ولا واحدة بتملا لي عينيّ\nجات هي حصل جنان شكلي هيتعلم عليّ\nلاء دي تعظيم سلام حلوة جدا مش عادية\n\n\n\n\n(محمود العسيلي)\nده الحب ملوش كبير\nوأنا إيه فاكر نفسي خبرة وبوقع ناس كثير\nوبعدي من خرم إبرة قال إيه جامد خطير\nخذت درس مية مية\n\n\n\n\n(تامر حسني & محمود العسيلي)\nطب هي دي إختراع قلبي راح غير مساره\nدي جمالها يجيب صداع كم برج من عقلي طاروا\nأيوة أم عيون فظاع ذبت جوة القلب ناره\nذبت جوة القلب ناره\n\n\n\n\n...\n\n\n\n\n(تامر حسني)\nطب حَبة حَبة قلبي شافها طب طبة\nده اللي كان مقفول بالضبة وترباس ومفيش دخول\n\n\n\n\n(محمود العسيلي)\nتأثير إلهي شد عقلي وانتباهي\nغيرت أنا اِتجاهي واتجننت مش معقول\n\n\n\n\n(تامر حسني & محمود العسيلي)\nطب هي دي إختراع قلبي راح غير مساره\nدي جمالها يجيب صداع كم برج من عقلي طاروا\nأيوة أم عيون فظاع ذبت جوة القلب ناره\nذبت جوة القلب ناره\n\n\n\n\n\n\n\n\n\n\n\n\n\n\n\n\n\n\n\n\n\n\nاستمع إلى \"اختراع (دويتو)\" على أنغامي","author":"احمد حسن راؤول","composer":"احمد زعيم","date":"2020","url":"https://fnanen.com/klmat/alaghany/t/tamr-7sny/a5tra3-doyto.html?arabic=اختراع (دويتو)"}