{"title":"الا انت","lyrics":"كلَّها الدنيا تخلّت ما بقى لي إلا أنتْ\n\nوانتْ كل الدنيا عندي لا تخلّيت أنتهي\n\nهاتها ايدك فديتك احضن كفوفي بصمتْ\n\nعاندت أحلام روحي بغير طيفك تلتهي\nإلا هذا الهجر تكفى ذابت حروفي عليكْ\n\nما بقت فيني صواري للحزن واستحمله\n\nإحتمال الوصل منّك للأسف يرجع إليـــكْ\n\nأما قلبي وانته تدري كيف ما يشتاق لـه\nوين ما قبّلت اشوفك وجهة جنون وخيالْ\n\nضعت في عيونك وتدري منهو غيرك اعشقه\n\nهيّه لحظه أيه وربّك بدّلت حالٍ بحالْ\n\nصرت لما انده عليهم اسمك أغلط وانطقه\n\n\n\n\n\n\n\n\n\n\n\n\n\n\n\n\n\n\n\n\n\n\nاستمع إلى \"الا انت\" على أنغامي","author":"ناصر البدري","composer":"خالد الشيخ","date":"2012","url":"https://fnanen.com/klmat/alaghany/f/fhd-alkbysy/ala-ant.html?arabic=الا انت"}