{"title":"الك وحشه","lyrics":"إلك وحشة يا أبو ضحكة الحلوة\n\nتعودنا عليك أشلون بلوى؟؟\n\nما نستغنى عنك يوم واحد\n\nلا راحة لنا بعدك و قوة\nإلك وحشة وغيابك ويل يا ويل\n\nوفراق العزيز يطول الليل\n\nحنانك بحر وأحلى ما به التدليل\n\nدللنا قضينا العمر قــســوة\nإلك وحشة و إلك لوعة وإلك آه\n\nإلك طلة وجه سبحانك الله\n\nأسألك يا حلو جاوبني بالله\n\nصحيح أنت ابن آدم وحوا؟؟\n\nما نستغنى عنك يوم واحد\n\nتعال وشوف هجرانك أيش سوا ؟؟\n\n\n\n\nكريم العراقي\n\n\n\n\n\n\nكاظم الساهر\n\n\n\n\n\n\n1997","author":"كريم العراقي","composer":"كاظم الساهر","date":"1997","url":"https://fnanen.com/klmat/alaghany/k/kazhm-alsahr/alk-o7shh.html?arabic=الك وحشه"}