{"title":"يا صلاة الزين","author":"بيرم التونسي","composer":"زكريا احمد","lyrics":"ياصلاه الزين ياصلاه الزين\nعلى الأمراء ياصلاه الزين ..\n\nياصلاه الزين ياصلاه الزين\nعلى الحلوين ياصلاه الزين ..\nياصلاه الزين ياصلاه الزين\nعلى الحاضرين يا صلاة الزين ..\nليلتهم حلوه ومحليها\nرب القدره ومنورها ..\n\nاخوان امراء وقصدناهم\nامراء و شعراء وجدناهم\nكيف البحرين ياصلاه الزين\nعلى الحلوين ياصلاه الزين\nيامية تحيه ايه\nيامية تحيه ايه ...\nقولوا على عزيزه بنت السلطان\nياصلاه الزين ياصلاه الزين\nعلى عزيزه ياصلاه الزين ..\n\nعزيزه شابه والله شابه\nشابه وشباب نواظرها تسحر الألباب\nوظفايرها والله شابه شابه حلوه\nوعندي الاكعاب ونفسنها تمره\nوشراب قمر ليله عشره واثنين\nياصلاه الزين على عزيزه ياصلاه الزين\nياصلاه الزين ياصلاه الزين ..\nعلى عزيزه ياصلاه الزين","url":"https://fnanen.com/klmat/alaghany/m/m7md-3bdalm6lb/ya-9lat-alzyn.html?arabic=%D9%8A%D8%A7%20%D8%B5%D9%84%D8%A7%D8%A9%20%D8%A7%D9%84%D8%B2%D9%8A%D9%86"}