{"title":"بحبك كل يوم اكتر","lyricist":"ايمن بهجت قمر","composer":"محمد يحيى","lyrics":"بحبك كل يوم اكتر من اليوم اللي كان قبلو\nبحبك و انت مستكتر عنيك و عينية يتقابلو\nبحبك كل يوم اكتر من اليوم اللي كان قبلو\nبحبك و انت مستكتر عنيك و عينية يتقابلو\nو امانة حبك في قلبي امانة\nحيعيش حبيبي هوانا\nدنته اللي بتمناه ..\nنسيني كل الي راح في سنيني\nو يا حلم شفتو في عيني\nلقيت كان حياتي معاه ..\nبحبك كل يوم اكتر من اليوم اللي كان قبلو\nبحبك و انت مستكتر عنيك و عينية يتقابلو\n---\nفي وقت ما تبقى عني بعيد بموت و انت اللي تحييني\nلقانا انا و انت اجمل عيد يا اغلى علية من عيني\nفي وقت ما تبقى عني بعيد بموت و انت اللي تحييني\nلقانا انا و انت اجمل عيد يا اغلى علية من عيني\nو امانة حبك في قلبي امانة\nحيعيش حبيبي هوانا\nدنته اللي بتمناه ..\nنسيني كل الي راح في سنيني\nو يا حلم شفتو في عيني\nلقيت كان حياتي معاه ..\nبحبك كل يوم اكتر من اليوم اللي كان قبلو\nبحبك و انت مستكتر عنيك و عينية يتقابلو","url":"https://fnanen.com/klmat/alaghany/m/m7md-7ma8y/b7bk-kl-yom-aktr.html?arabic=%D8%A8%D8%AD%D8%A8%D9%83%20%D9%83%D9%84%20%D9%8A%D9%88%D9%85%20%D8%A7%D9%83%D8%AA%D8%B1"}