{"title":"ناس كثير","lyrics":"ناس كثير يرتاحوا فينا\nوناس تقاسي من التعب\nالسنين تضحك عليهم\nوالزمان يغدر هواهم\nيتنسوا حتى في كلام\nيتنسوا بين الزحام\nقلبهم مجروح يإن\nدمعهم دايم يحن\n \nضاعوا في الليل والجروح\nفي الاسى وغلب الزمن\nيسألوا مافي جواب\nمافي انسان يفتكرهم\nمافي فرحه بتنتظرهم\nيقضوا ايام العذاب والضياع\nوالغربه وبحور الضنى\nيضحكوا للناس ويبكوا بقلبهم\nالامل يعطوه هديه وهم عايشين في العنا\n \nناس تسافر تسترح بعد السفر \nتنسى كيف كان الوداع\nتنسى ليل كلو ضياع\nواللي عاشوا لوحدهم\nواللي سهروا بدمعهم\nسهروا حتى السهر\nودعوا نور القمر\n \nلا اهل في الدنيا حتى بيرحموا\nلا صديق ولا حتى واحد في الطريق\nيسأل عليهم او يكون دربه رفيق\n\n\n كلمات:\n\n\n\n\n\n\n ألحان:","author":"امين قطان","composer":"احمد صدقي","url":"https://fnanen.com/klmat/alaghany/a/abtsam-l6fy/nas-kthyr.html?arabic=ناس كثير"}