{"title":"اورفوار","lyrics":"اورفوار مابغيتك انا مابغيتك حدايا\nاورفوار مليت اللي درتو درتو معايا\nاورفوار هذلك الحب اللي كان وعرفتو\nاورفوار وصلني معاه لطريق النهايه\nياغدار مابغيتك تجي وتوصل لجنبي\nياغدار مابغيتك تحلم تحلم بقربي\nوعيش النار بعد ماولفتي تعيش بهنايا\nاورفوار مابغيتك مابغيتك حدايا\nبسلاما بسلاما سير دير راسك بسلاما بسلاما\nيا لكييده شاهدين اهلك وناسك بلاش الملامه\nوالعمر اشرب من مر كاسك وكافي دراما\nسير عني وحيدني من راسك خليني ننساك\nيكفي لعذاب اللي جاني منك مليت انا اهواك\nراه بغيت انعيش انا حياتي بعيد عنك\nاورفوار مابغيتك مابغيتك حدايا\n\n\n كلمات:\n\n\n\n\n\n\n ألحان:\n\n\n\n\n\n\n تاريخ:\n\n\n\n\n\n\n\n\nاستمع إلى \"اورفوار\" على أنغامي","author":"مصعب العنزي","composer":"عبدالله السالم","date":"2011","url":"https://fnanen.com/klmat/alaghany/m/mna-amrsha/aorfoar.html?arabic=اورفوار"}