{"title":"تكلمنا","author":"سلطان الجمعان","composer":"احمد الفهد","date":"2008","lyrics":"تكلمنا بحسن نيه ماندري عن نواياهم\nخطا ظنينا كل الناس يحبوني ويحبونك\n\nحسبنا الناس تهوانا مثل مااحنا نهواهم\nأثاريهم من الغيره يحسدوني ويحسدونك\n\nمحد جانا وعلمنا انا وياك شفناهم\nهدفهم أفقدك وأبقي حياتي كلها بدونك\n\nتري اكبر دليل اللي حصل بالامس وياهم\nماشفت عيونهم ترسل سهام الغيره لعيونك\n\nخساره تنصدم في ناس فرشت الدرب لخطاهم\nوهم بارخص تراب الأرض يبيعوني ويبيعونك\n\nأنا أسال عن العشره وأفتش في هداياهم\nتجاوبني وهي تبكي اهم كانو يغشونك","url":"https://fnanen.com/klmat/alaghany/r/rab7-98r/tklmna.html?arabic=%D8%AA%D9%83%D9%84%D9%85%D9%86%D8%A7"}