{"title":"ارحميني","lyrics":"يا عيوني ليه تبكين الحبيب\n\nارحميني لا تزيديني عذاب\n\n\n\nيا عيوني بالهنا مالي نصيب\n\nخان عهده صاحبي عقب الغياب\n\n\n\nإن بعثنا له رسايل ما يجيب\n\nلو يبينا ما بخل يرسل جواب\n\n\n\nما رحم مجروح بالغربه صويب\n\nوا حسايف باعني غض الشباب\n\n\n\nسلوتي ابيات شعري والنحيب\n\nصرت احسب للقاء مية حساب\n\n\n\nتاه حبي ليه فعله ذا عجيب\n\nكيف ينسى صاحبي عقب الغياب\n\n\n\nتب يا قلبي الهوى دربه صعيب\n\nوالسعاده فيه نادر تستجاب\n\n\n\n\nخالد بن يزيد\n\n\n\n\n\n\nسعودي\n\n\n\n\n\n\n1984","author":"خالد بن يزيد","composer":"سعودي","date":"1984","url":"https://fnanen.com/klmat/alaghany/3/3tab/ar7myny.html?arabic=ارحميني"}