{"title":"يا هل الله دلوني","lyrics":"يا هل الله دلوني على الغالي\n\nولع النار في قلبي وخلاني\n\n\n\nويش اسوي بعد ما غاب عن عيني\n\nاتصبر وكان الله في عوني\n\n\n\nما تعودت بعد اليوم حبيتك\n\nاو خطر لي بعد روحي ينساني\n\n\n\nبلغوا نور عيني لا يخليني\n\nلا يطول .. بغيابه ويجفاني\n\n\n\nماتوقعت نور عيني يخليني\n\nولا تمنيت غيره سيد خلاني\n\n \n\n\n كلمات:\n\n\n\n\n\n\n ألحان:\n\n\n\n\n\n\nاستمع إلى \"يا هل الله دلوني\" على أنغامي","author":"هاني فيروزي","composer":"طاهر حسين","url":"https://fnanen.com/klmat/alaghany/7/7ydr-fkry/ya-hl-allh-dlony.html?arabic=يا هل الله دلوني"}