{"title":"تحياتي","author":"محمد يحيى","composer":"جمال ياسين","date":"2018","lyrics":"هصرف نظر عنك وخد بالك كمان\nناوي اني اسيبك وامشي وابعد من زمان\nمضعفش انا في بعدك وتجرحني عشان\nدي حكايه ولا تسوى\nعاوز اشكرك علشان انا اتعلمت فيك\nمش جاي ألومك ولا جاي اعتب عليك\nجرحي اللي كان منك وعشته أنا بين ايديك\nانا بيه بقيت اقوى\nتحياتي ..\nهرسم طريق تاني لحياتي .. وابعد واسيبلك ذكرياتي\nعلى الله قلبك مرة من نفسي اوجعه\nتحياتي ..\nراجع وبتداري في كسوفك .. إنده متسمعش الا صوتك\nواشك انك حتى ممكن تسمعه\nتحياتي ..\n...\nمبروك عليك اقبل خسارتك بعدها\nومتعيش دور الغلبنة والمسكنة\nواللي انت جاي علشان تشوفه مش هنا\nوانسى اللي بينا خلاص\nتَحِيّاتِي ..\nهرسم طريق تاني لحياتي .. وابعد واسيبلك ذكرياتي\nعلى الله قلبك مرة من نفسي اوجعه\nتحياتي ..\nراجع وبتداري في كسوفك .. إنده متسمعش الا صوتك\nواشك انك حتى ممكن تسمعه\nتحياتي ..","url":"https://fnanen.com/klmat/alaghany/a/abrahym-al7kmy/t7yaty.html?arabic=%D8%AA%D8%AD%D9%8A%D8%A7%D8%AA%D9%8A"}