{"title":"حبيب الحب","author":"فيصل بن خالد بن سلطان","composer":"رابح صقر","lyrics":"حبيب الحب يالحب وحبيبي\nنفس روحي بعد روحي وحالي\nعسى دايم .. وشمسك ما تغيبي\nعن عيوني وعن قلبي وبالي\n\nاذا بعدك قدر هذا نصيبي\nواذا حظي قدر يا طيب فالي\nسنين العمر تسألني وأجيبي\nعلى ذكراك وحضورك سؤالي\n\nتواريخك تمر وتلتقي بي\nوتنساني وتذكرك الليالي\nأحسك حيل من قلبي قريبي\nعساني مانحرم شوفق قبالي\n\nشموعك كل ليله تحتفي بي\nلقلبي ضي ولعمري ظلالي\nعرفت الحب منك يا حبيبي\nوشكرا لك يا حبي لحالي","url":"https://fnanen.com/klmat/alaghany/m/m7md-3bdh/7byb-al7b.html?arabic=%D8%AD%D8%A8%D9%8A%D8%A8%20%D8%A7%D9%84%D8%AD%D8%A8"}