{"title":"عذبة انتي","lyricist":"ابو القاسم الشابي","composer":"محمد عبده","date":"1989","lyrics":"عذبة أنت كالطفولة كالأحلام\nكاللحن كالصباح الجديد\n\nكالسماء الضحوك .. كالليلة القمراء\n.......كالورد .. كابتسام الوليد\n\nأنت أنت .. أنت ما أنت؟\n....أنت رسم جميل عبقري من فن هذا الوجود\n\nأنت تحيين في فؤادي ما قد مات\n.......من أمسي السعيد الفقيد\n\nوتبثين رقة الشوق والأحلام\n.....والشدو والهوى في نشيدي\n\nيالها من وداعة وجمال\n....وشباب منعّم أملود\n\nأنت روح الربيع تختال في الدنيا\n.....فتهتز رائعات الورود","url":"https://fnanen.com/klmat/alaghany/m/m7md-3bdh/3zabt-anty.html?arabic=%D8%B9%D8%B0%D8%A8%D8%A9%20%D8%A7%D9%86%D8%AA%D9%8A"}