{"title":"ماهو عادي","lyricist":"عبدالرحمن بن مساعد","composer":"صادق الشاعر","lyrics":"كان هالليلة بهاكي ماهو عاديكنتي أنتي وانتي لما تكوني أنتي ماهو عادي\nكنتي اعجاز وسحر .. كنتي دنيا من طهر\nكان نورك في جبين الكون بادي\nكان في صمتك طرب .. وكان في عيونك شغب\nكان حسنك للحسن يرسي مبادي\nكنتي في أجمل حضورك .. كني في أعدل غرورك\nلما طافت بي عيونك .. وأستقرت في فؤادي\nكنت أنا أتأملك .. وكنت أنا اتخيلك\nوأنتي معي والكون هادي\nكان أحساسي مهيب\nكنت أحس أني مهاجر أو غريب\nوأنتي يا عمري بلادي\n\n---\n\nآه لو باكر لأمسي يلتجي .. يترك الليلة ليالي وما يجي\nآه أنا من غدر باكر كم أخاف .. ياخذك مني وأنا لقلبي شغاف\nحزنها في غيبتك مر و شجي\nآه أنا من غيرك أنتي وش وجودي .. آه أنا كم أبغى باكر لو تعودي\nآه من ذكرى بتشعل بي سهادي\nلما كنت أتأملك .. ولما كنت أتخيلك\nوأنتي معي والكون هادي\nكان أحساسي مهيب\nكنت أحس أني مهاجر أو غريب\nوأنتي يا عمري بلادي\n\n---\n\nيا ملاذي ومنتهاي و أولي .. ايه أحبك فوق ما تتخيلي\nليت أنا يا بعد قلبي لي قلوب .. لأجل ما في كل لحظة بك أذوب\nكل إجاباتك أنا لا تسألي\nما أبي شمسك يواريها مغيب .. لو جروحي منك ما ودي تطيب\nياللي سعدك منتهى غاية مرادي\nآه كم أشتاقلك .. آه كم أحتاجلك\nآه كم أشتاقلك وأحتاجلك .. في القرب وأكثر في بعادي\nأنتي أحساسي الاكيد\nوأنتي دمي اللي بيجري في الوريد\nأنتي يا عمري بلادي","url":"https://fnanen.com/klmat/alaghany/m/m7md-3bdh/maho-3ady.html?arabic=%D9%85%D8%A7%D9%87%D9%88%20%D8%B9%D8%A7%D8%AF%D9%8A"}