{"title":"برشا","lyrics":"برشا برشا يا مدلل .. برشا برشا\nحبك على قلبي تسلل .. برشا برشا\nمن عيني لو ردت تروح\nجسمي وروحي تتعلل\nانا حبي ليك برشا\nوروحي ولهانه وعطشى\nوقلبي سلملك عرشا\nوعقلي بحكمك يتامل\nبرشا الشوق ملوعني\nيؤمرني ويطوعني\nحبيب القلب اسمعني\nوكافي علي تدلل\nانا حبي ليك برشا\nوروحي ولهانه وعطشى\nوقلبي سلملك عرشا\nوعقلي بحكمك يتامل\nنظره هالعين الكحلا\nبواب القلب بتفتحلا\nياريت اقدر لمحلا\nوالحب يصير محلل\nانا حبي ليك برشا\nوروحي ولهانه وعطشى\nوقلبي سلملك عرشا\nوعقلي بحكمك يتامل\nبرشا برشا يا مدلل.. حبك على قلبي تسلل","author":"كمال","composer":"صابر الرباعي","url":"https://fnanen.com/klmat/alaghany/9/9abr-alrba3y/brsha.html?arabic=برشا"}