{"title":"امير الظلام","author":"مجدي كامل","composer":"خالد حماد","date":"2005","lyrics":"النور مكانه في القلوب\nاحضن خيوط  شمس الغروب\nيا تكون قد الحياة\nيا تعيش وحيد وسط الدروب\nاليأس ضعف وخوف جبان\nلاكن الامل يفتح بيبان\nيا تكون قد الحياة\nيا تعيش وحيد وسط الدروب\nالمس فضاء الشجر\nحس بضياء القمر\nانقش قلوب ع الحجر\nعلى شيء ما تندمش\nيمك قوام عديه\nامشي الطريق امشيه\nالعمر ارويه غير قلب ما يخافش\nالنور مكانه في القلوب\nاحضن خيوط  شمس الغروب\nيا تكون قد الحياة\nيا تعيش وحيد وسط الدروب\nفي ناس كتير ترضى المصير\nوناس تشوف بضمير ضرير\nيا تكون قد الحياة\nيا تعيش وحيد وسط الدروب\nحلي مرار الايام\nلسه الحياة قدام\nقوم لون الاحلام\nواوعى ما تضحكش\nده ابن ادم في قلبه الروح\nيداوي كل جروح\nبالسر اوعى تبوح واياك ما تحلمش","url":"https://fnanen.com/klmat/alaghany/m/md7t-9al7/amyr-alzhlam.html?arabic=&#x627;&#x645;&#x64A;&#x631; &#x627;&#x644;&#x638;&#x644;&#x627;&#x645;"}