{"title":"طبول المكلا","lyricist":"مريم العبدلي","composer":"يوسف المهنا","date":"2004","lyrics":"بجلي همومي وبلعب وبسلا ... مالي من الهرج والقيل والقال\nوابا طبول ٍ من طبول المكلا ... بنظم بها الشرح والدان والبال\nوادان وادانه ... ابآ طبول المكلا وابآ الدان\n\nبفرح مع الزين ابو عيون كحله ... لي خذ معه القلب والروح والمال\nقلت فين ذا اللي قد سحرني وولى ... ولى وخلا معي شغلة البال\nوادان وادانه ... ابآ طبول المكلا وابآ الدان\n\nتوبه من الحب توبه وبحلا ... لي هم قلبي وحملني الأثقال\nويا حبيبي دلابي تدلى ... يكفي عذابي ودمعي الذي سال\nوادان وادانه ... ابآ طبول المكلا وابآ الدان\n\nجاني وقال جيت عسى الهم يجلى ... ماشي صبر جيت من غير مرسال\nرحبت به قلت اهلاً وسهلا ... يا نسب جدي مع العم والخال\nوادان وادانه ... ابآ طبول المكلا وابآ الدان","url":"https://fnanen.com/klmat/alaghany/a/aroa/6bol-almkla.html?arabic=%D8%B7%D8%A8%D9%88%D9%84%20%D8%A7%D9%84%D9%85%D9%83%D9%84%D8%A7"}