{"title":"رجال احلا من المال","lyrics":"الرجال احلا من المال الله يبارك بالرجال\n\nمن الصخرة بيطلع مي وبزنوده بيهد جبال\n\nالله يبارك بالرجال\nيسلم لي الزند المفتول والقامة الحلوة والطول\n\nوعيون اللي اتضل تقول ياحلوة لاترمي نبال\n\n \n\nمن الصخرة بيطلع مي وبزنوده بيهد جبال\n\nالله يبارك بالرجال\nالله يحمي هالجبار لو منه ماتعمر دار\n\nولا كان صار الليل نهار ولا كان تغني موال\nمن الصخرة بيطلع مي وبزنوده بيهد جبال\n\nالله يبارك بالرجال\n(موال) :\nتسلم ياجسر البيت تسلم ياملك\n\nهالبيت طول العمر راح يبقى الك \n\nولو صار شو ماصار يارفيقي الحبيب\n\nبكل مال الكون مش راح ببدلك \nالرجال هدية الله وزينة هالدنيا كلا\n\nعنو مش راح نتخلى ولا منعيش بلا رجال\n\nالله يبارك بالرجال\n\n\n كلمات:\n\n\n\n\n\n\n ألحان:\n\n\n\n\n\n\nاستمع إلى \"رجال احلا من المال\" على أنغامي","author":"توفيق بركات","composer":"محمد محسن","url":"https://fnanen.com/klmat/alaghany/9/9ba7/rjal-a7la-mn-almal.html?arabic=رجال احلا من المال"}