{"title":"ع الصوره امضي","lyrics":"ع الصورة امضي لي عَ الصورة زينها بوردة زغيورة\n\nودي لي الصورة يا حبيبي ع جوانج نسمة وعصفورة\n\nعَ الصورة امضي لي عَ الصورة\nلو تسأل قلبك بيقول لك وبتعرف إني اشتقت لك\n\nبعدك جنني يا حبيبي\n\nما بتسأل عني يا حبيبي\n\nبضحك وبغني يا حبيبي وجوانح قلبي مكسورة\n\nعَ الصورة امضي لي عَ الصورة\nيا سارق قلبي من قلبي ورايح ولا سائل على حبي\n\nما بعرف وينك يا حبيبي\n\nتسلم لي عينك يا حبيبي\n\nما بيني وبينك يا حبيبي في ألف حكاية وحزورة\n\nعَ الصورة امضي لي عَ الصورة\nعلى فكرة وقبل ما إنسى مش لازم يا حبيبي تقسى\n\nتذكر ماضينا يا حبيبي\n\nشو رحنا وجينا يا حبيبي\n\nورجع ليالينا يا حبيبي وارجع لي وما بدي الصورة\n\nعَ الصورة امضي لي عَ الصورة\n\n\n كلمات:\n\n\n\n\n\n\n ألحان:\n\n\n\n\n\n\n تاريخ:\n\n\n\n\n\n\n\n\nاستمع إلى \"ع الصوره امضي\" على أنغامي","author":"ميشال طعمه","composer":"فريد الاطرش","date":"1973","url":"https://fnanen.com/klmat/alaghany/9/9ba7/3-al9orh-amdhy.html?arabic=ع الصوره امضي"}