{"title":"وين اخذك","lyricist":"كريم العراقي","composer":"كاظم الساهر","date":"1997","lyrics":"وين آخذك .. وين أنهزم بيك\nبضلوعي لو بعيوني أخليك\nجابتك واتبسمت أمك\nوأنا على راسي شلت همك\nهي الل عليها سمت أسمك\nوآنا الل عليّ أبتلي بيك\nوين آخذك يا أغلى مني؟؟\nحيرة وغيرة جننّي\nلا .. لا تظن أرقص وأغني\nرجف الخلاخل أرجف عليك\nوين آخذك عيونك دواهي\nهي الجرح وهي الدوى هي\nسهرني حيرني يا لاهي\nإن كان هذا الحال يرضيك\n(موال) :\nعجبي على حرفين قد سلبا وقاري\nحاء حريق وباء بت في ناري\nماذا جرى لي؟؟\nنحول .. غيرة.. قلق.. سهر.. عذاب\nجنون هزّ أفكــاري\nيا با يابا يا عيوني","url":"https://fnanen.com/klmat/alaghany/k/kazhm-alsahr/oyn-a5zak.html?arabic=%D9%88%D9%8A%D9%86%20%D8%A7%D8%AE%D8%B0%D9%83"}