{"title":"بعيد عنك","lyrics":"بعيد عنك ثواني ومش قادر احس بيك\nجنبي وانت نايم وبخاف اقرب ليك\nبمد ايدي لإيدك ترجع تشيلها ليه\nمعاك كنت أناني جرحتك مش عارف ليه\nقول بس قول مش عايزك تبصلي\nصمتك بيعذبني عارف انا المسئول\nاديني فرصه تانية اوريك اني محتاجلك\nوان بعدك مفيش حياة\n\n\n كلمات:\n\n\n\n\n\n\n ألحان:\n\n\n\n\n\n\n تاريخ:\n\n\n\n\n\n\n\n\nاستمع إلى \"بعيد عنك\" على أنغامي","author":"يوري مرقدي","composer":"يوري مرقدي","date":"2015","url":"https://fnanen.com/klmat/alaghany/y/yory-mr8dy/b3yd-3nk.html?arabic=بعيد عنك"}