{"title":"البلبل والزهرة (دويتو)","lyricist":"زين العابدين عبدالله","composer":"يوسف شوقي","lyrics":"(عبدالحليم حافظ):\nيازهره نديّه يازهره نديّه .. يازهره نديا يازهره نديّه\nيانايمه وحسنك بيشفي العيون ..\nماتصحي يازهره وردي عليّا .. بصبّح عليك بصوتي الحنون\n\n(عصمت عبدالعليم):\nيابلبل ياشادي .. يااسر فؤادي .. بنور الصباح\nصباحك جمال .. مشفتش مثاله .. يزيدني انشراح\n\n(عبدالحليم حافظ):\nنهارك ده نادي .. وجيتك انادي .. ببهجه وسرور\nصباح المحبه .. لكل الأحبه .. ياست الزهور\n\n(عصمت  & عبدالحليم):\nفي صوتك اماني .. في حسنك معاني\nولحنك اسرني .. ولونك سحرني ..\nوشمس النهار ده .. في كونها جميله\nوطالعه تهني جميع العباد\n\n(عبدالحليم حافظ):\nريحتك يازهره تخلي الخميله .. دي جنه بيسعد معاها الفؤاد\n\n(عصمت عبدالعليم):\nصوتك بيسري ويطفي الطبيعه .. بـ ثوب المسره وثوب الجمال\n\n(عبدالحليم حافظ):\nوكل الجمال زهورها بديعه .. في نشوة عبيرها يتوه الخيال\n\n(عصمت  & عبدالحليم):\nيامحلا النهار ده في حسنه ونعيمه\nده غنوه جميله يقولها السعيد\nيامحلا النهار ده في رقة نسيمه\nده فرحه وبهجه وسلوى وعيد\nصباح التهاني لكل الوجود .. صباح الأغاني بسحر وصفاء\nبشمس واغاني وزهر وورود .. قلوبنا بتسعد وتحلا الحياة","url":"https://fnanen.com/klmat/alaghany/3/3bdal7lym-7afzh/alblbl-oalzhrt--doyto-.html?arabic=%D8%A7%D9%84%D8%A8%D9%84%D8%A8%D9%84%20%D9%88%D8%A7%D9%84%D8%B2%D9%87%D8%B1%D8%A9%20(%D8%AF%D9%88%D9%8A%D8%AA%D9%88)"}