{"title":"الزم حدودك","author":"تركي","composer":"طارق محمد","lyrics":"ولا كلمه بعد الزم حدودك\nبعد لك عين يا خاين عهودك\nتوهقت وتماديت بجهاله\nتوقى عاد لا ويلي يطولك\n\nانا فوت لك ياما وياما\nوغالط اللي ينصحني بعوامه\nوظنيتك وفي قلبي وغرامه يالندامه\nولكن للأسف تهت بغرورك\n\nانا حبيتك  وحبيت لنفسي\nترى حبك بعض حبي لنفسي\nتظن أغليك وارخص حيل نفسي\nحبيبي لي متى ظنك يخونك","url":"https://fnanen.com/klmat/alaghany/3/3adl-5mys/alzm-7dodk.html?arabic=&#x627;&#x644;&#x632;&#x645; &#x62D;&#x62F;&#x648;&#x62F;&#x643;"}