{"title":"يا اهل الخير","author":"خالد العوض","composer":"بدر الذوادي","date":"2012","lyrics":"يا اهل الخير دلوني\nاقروآ علي والا داووني\nالقلب شبت به نيرانه\nكيف الحبايب يخلوني\n\nاللي عطيته انا عمري\nضيع حياتي وكسر ظهري\nنسى جروحه بوسط صدري\nبكى لي قلبي مع عيوني\n\nفي تالي الليل انا ساهر\nوالحال تصعب على الكآفر\nشكواي انا مالها اخر\nيالله تفرج لي حزوني","url":"https://fnanen.com/klmat/alaghany/h-/hnd/ya-ahl-al5yr.html?arabic=&#x64A;&#x627; &#x627;&#x647;&#x644; &#x627;&#x644;&#x62E;&#x64A;&#x631;"}