{"title":"كل ليله","lyricist":"فائق حسن","composer":"حسن فالح","date":"2006","lyrics":"(موال) :\nيمر الليل بعدك يا حبيبي كل لحظة تعادل لي زماني\nأعانق وحدتي وأذوب شوقاً ياريتك صرت مرة بمكاني\n\nكل ليله أفكر بيك وحدي .. لو تدري قلبي شسوى بيه\nشلون شلون بيه شلون\nدفيان لو بردان بعدي .. أني اللي ربيتك بإيديا\nشلون شلون بيه شلون\nفدوة أروح أني لعيونك .. صدقني ما عايش بدونك\nياللي إنت ساكن وسط روحي .. وأقرب صرت مني عليا\nشلون شلون بيه شلون\n\nحنيت قلي وينك إنت .. بعد السما صاير عليا\nشلون شلون بيه شلون\nمن وين أجيبك تعب قلبي .. بس ليله لو نقعد سويه\nشلون شلون بيه شلون\n\nأسأل عليك أنجرح صوتي .. مثل الطفل ومضيع أمه\nشلون شلون بيه شلون\nلو شفت أنا خالي مكانك .. يذوب القلب من كثر همه\nشلون شلون بيه شلون","url":"https://fnanen.com/klmat/alaghany/m/majd-almhnds/kl-lylh.html?arabic=%D9%83%D9%84%20%D9%84%D9%8A%D9%84%D9%87"}