{"title":"اخر حاجه","lyrics":"كلمه في قلبي شايلها ليك .. ياللي عمري احلو بيك\n\nنفسي اقولك ياحبيبي .. واعترف وانا بين ايديك\n\nانت اللي قلبي حس بيك .. وحلم عمري لقيته فيك\n\nاتمنى ايه ياحبيبى تاني .. كل الامانى لقتها فيك\n\n \n\nبحبك انت آخر حاجه .. انا روحي ليك دايما محتاجه\n\nانا لو هقول فيك الكلام يطول .. حبيبي دا انت عندي اغلى حاجه\n\nانا روحى عاشقه ومرتاحالك .. وعيوني دايما مشتاقالك\n\nوياك بعيش احلام متنتهيش .. وحياتي ليك انا عشتهالك\nانا لو هقول دا قليل عليك .. اجمل مافيك ضحكة عنيك\n\nيالا تعالى حبيبي قرب .. كل ما فيا بيناديك\n\nوديني دنيا مروحتهاش .. عيشني لحظه معيشتهاش\n\nوانا بين ايديك بتكون واحشني .. وانت معايا بشتاق اليك\n\nليله وانا كل ليله معاك .. حبيبى مقدرش يوم انساك\n\n \n\nفى بالي طول الليالي .. حبيبي دا انت ارق ملاك\n\nبحبك انت آخر حاجه .. انا روحي ليك دايما محتاجه\n\nانا لو هقول فيك الكلام يطول .. حبيبي دا انت عندي اغلى حاجه\n\nانا روحى عاشقه ومرتاحالك .. وعيوني دايما مشتاقالك\n\nوياك بعيش احلام متنتهيش .. وحياتي ليك انا عشتهالك","author":"طاهر كامل","composer":"اشرف سالم","date":"2010","url":"https://fnanen.com/klmat/alaghany/7/7madh-hlal/a5r-7ajh.html?arabic=اخر حاجه"}