{"title":"مالي مزاج في الكلام","lyrics":"مالي مزاج في الكلام\n\nومالو هوى في بالزياره\n\nمسكين ياعيني الغرام\n\nبدلنا فرحو بمراره\n\nوقفلنا باب العتاب\n\nورضينا شوق الغياب\n\nماقلنا حتى خساره\n\n\n\nمرت يوم ويومين\n\nماحد فينا تكرم\n\nعلى حبي أبكي فعين\n\nوحب قلبي تألم\n\nفرق مابينا الغرور\n\nضيع طريق الهنا\n\nوبدلنا ليل الدموع\n\nفعينك وقلبي أنا\n\n\n\nمدري نسيتني صحيح\n\nوإلا أنت زيي تداري\n\nحاسس بأني جريح\n\nليلي يواصل نهاري\n\nمستني لحظة رجوع\n\nتمحي مساوئ ظنوني\n\nواتمنى لحظة هدوء\n\nوتضم عينك عيوني\n\n\n كلمات:\n\n\n\n\n\n\n ألحان:","author":"صالح جلال","composer":"فوزي محسون","url":"https://fnanen.com/klmat/alaghany/f/fozy-m7son/maly-mzaj-fy-alklam.html?arabic=مالي مزاج في الكلام"}