{"title":"حبيبي يامحلاه","lyricist":"وسيم باسعد","composer":"ناصر الصالح","lyrics":"ياحبيبي يامحلاه مو بس حلو يا ناس\nالله عليه الله\n\nياويلي من زينه .. ما احلى هدب عينه\nكل ما التفت صوبي .. مجبور ثاني اهواه\n\nلو غيره يحصلي .. ماغيره هو وخلي\nحسبي عليه حسبي .. لو باعني ويلاه\n\nطب ودوآ جروحي .. عمري وبعد روحي\nوان قال لي عمري .. كل العمر يفداه\n\nياحبيبي يامحلاه مو بس حلو يا ناس\nالله عليه الله","url":"https://fnanen.com/klmat/alaghany/m/m7md-alzyl3y/7byby-yam7lah.html?arabic=%D8%AD%D8%A8%D9%8A%D8%A8%D9%8A%20%D9%8A%D8%A7%D9%85%D8%AD%D9%84%D8%A7%D9%87"}