{"title":"علشان اهواك","lyricist":"دعيج الخليفه الصباح","composer":"فهد الناصر","date":"2010","lyrics":"صدقني يا روح الروح .. لو بتعيشني جروح\nانا راضي حبيبي راضي حبيبي .. بس علشان اهواك\nمو بيدي اني ابيك .. ودموعي ميته فيك\nونصيبي وهو نصيبي يا غالي .. ما يرضى بفرقاك\nانا من شفتك كل حياتي واماني ..\nراضي لو بتجرحني وقلبي يعاني ..\nيا مخليني اغني بحبك اغاني ..\n---\nانا ما ودي في يوم .. انته تخليني\nامنيتي تسكن .. على طول في عيني\nلانك تدري .. معاك يتحلي سنيني\nصدقني يا روح الروح .. لو بتعيشني جروح\nانا راضي حبيبي راضي حبيبي .. بس علشان اهواك","url":"https://fnanen.com/klmat/alaghany/a/a7md-7syn/3lshan-ahoak.html?arabic=%D8%B9%D9%84%D8%B4%D8%A7%D9%86%20%D8%A7%D9%87%D9%88%D8%A7%D9%83"}