{"title":"الشهيد","author":"نصر الدين ناجي","composer":"احمد فرحات","date":"2017","lyrics":"لو ع الحزن بنعرف نحزن بس مفيش للحزن مكان\nإبني هيفضل جوه في قلبي صوره بتضحك بالألوان\nلسه بيتنفس حريه حي في عيني لا غاب ولا راح\nلسه ملامحه في وش أخواته صبر وحلم وشوق وكفاح\nعايش في ورد الأرض إللي بيطرح\nفي ضحكة عين طفل بيفرح\nفي قلب الناس اللي بتيجي وبتروح\nقضى عمره سنين والضحكه رسماله\nولسه الضحكه بقياله في حضن النور\nوالنور ميسعش كلام مجروح","url":"https://fnanen.com/klmat/alaghany/m/m7md-mnyr/alshhyd.html?arabic=%D8%A7%D9%84%D8%B4%D9%87%D9%8A%D8%AF"}