{"title":"حبيبي لولا السهر","lyrics":"حبيبى لولا السهر      ما حد شاف القمر\n\nولولا جرح الهوى ما كان له طعم الهوى\n\nواشوفك يا عيون حبيبى تحلالي نار الهوى\n\n***\n\nيغيب القمر ويطل القمر\n\n ما يلقاش حبيبي يزعل القمر\n\n ولا يحلى السهر\n\n من غيرك حبيبي يا اجمل قمر\n\n  كفاية سفر\n\n وارجع يا حبيبى. وان غاب القمر\n\n نبعت له خبر\n\n يرجع يا حبيبى\n\nواشوفك يا عيون حبيبي تحلالي نار الهوى\n\n***\n\nالنجمة البعيدة شافتنى وحيدة\n\n جات تسأل عليَّ وباست عينيَّ\n\nقالت لي حبيبك باعت لك هدية\n\n بيقول لك بحبك قد الدنيا ديه\n\nواشوفك يا عيون حبيبي تحلالي نار الهوى\n\n***\n\nواحشني يا حبيبي\n\n امتى يا حبيبي  ندوب الفراق\n\nوانسى معاك حياتي\n\n وانسيك يا حياتي قسوة الفراق\n\n\n\n\nمرسي جميل عزيز\n\n\n\n\n\n\nمحمد الموجي","author":"مرسي جميل عزيز","composer":"محمد الموجي","url":"https://fnanen.com/klmat/alaghany/n/njat-al9ghyrh/7byby-lola-alshr.html?arabic=حبيبي لولا السهر"}