{"title":"اعراس","author":"محمود درويش","composer":"مارسيل خليفه","date":"1979","lyrics":"رجل يسقط تحت الكلمات السابقة\nما الذي يفعله، دمه يحمله\nويسير ويسير وتكون الصاعقة\nطفلة تحبو على حقل شظايا نازلة\nتتمشى جسمها وتنادي أمها، وتطير في غبار القافلة\nولد يهرب من درس القراءة\nلم يواصل كسله، مزقته طائرة\nمن هواء البحر حتى السنبلة\nعاشق يأتي من الحرب إلى يوم الزفاف\nيرتدي بذلته الأولى ويدخل\nوعلى حبل الزغاريد يلاقي فاطمة\nوتغني لهما مناديل الحداد الناعمة\nوعلى سقف الزغاريد تجيء الطائرات\nطائرات\nطائرات\nتأخذ العاشق من حضن الفراشة\nومناديل الحداد\nوتغنّي الفتيات\nيا محمّد\nقد تزوّجت البلاد….","url":"https://fnanen.com/klmat/alaghany/m/marsyl-5lyfh/a3ras.html?arabic=%D8%A7%D8%B9%D8%B1%D8%A7%D8%B3"}