{"title":"ليش","lyricist":"غانم فارس","composer":"عبدالله المناعي","date":"2006","lyrics":"ليش انت متكدر وضايق\nليش انت تشكي من هالزمان\nوتقول ان الدنيا ما فيها\nغير هم واحزان\nالدنيا والله بخير\nبس انت خل قلبيك كبير\nواصبر على حزنك وهمك\nترى اللي يصبر اجره كبير\nهونها وانسى كل همومك\nواضحك وعيش بالفرح يومك\nولا تشيل همك وسط قلبك\nتسهر ولا تهنى في نومك\nمن فينا ما عمره تضايق\nمن فينا باله دوم رايق\nبس لازم نتحمل ونصبر\nونضحك ولو حتى دقايق\nليش انت متكدر وضايق\nليش انت تشكي من هالزمان\nوتقول ان الدنيا\nما فيها غير هم واحزان","url":"https://fnanen.com/klmat/alaghany/f/fhd-alkbysy/lysh.html?arabic=%D9%84%D9%8A%D8%B4"}