{"title":"ياشيخ قفاعه","author":"بديع خيري","composer":"سيد درويش","lyrics":"اقرأ ياشيخ قفاعة تلغراف آخر ساعة\nاللي في جورنال البورص\nوأنا أبقى أحلق ذقني إن ماكنتش ترقص\nترقص ترقص ترقص\nالصبح صبح قلسطة والعيشة هتبقى قشطة\nياقساتذة قولم هش\nياقساتذة قولوا براوة دي الحرب خلاص فينيشٌ\nفينيشٌ فينيشٌ فينيشٌ\nبعد أكل التسقية والسلطة والطعمية\nاللي بتهد الحيل\nنرقع لنا اقتين ثلاثة من لحم الخيل ارقع\nارقع ارقع ارقع\nياما بكرة حنبقى نقلّس ع التجار لما تفلس\nوزي مانتفلق\nيتفلقوا هما كمان واحنا نضحك هقهق\nهقهق هقهق هقهق\nومادام الضاني غالي وكذلك العجالي\nمش لازم ندقق\nحصانا أو حمارا أوبغلا مش راح نعتق قبدا\nقبدا قبدا قبدا\nيالا نقلوظوا العمة ألا مودا ونستحمى\nبصفيحة كالونيا\nونسافر على أوروبا نتفرج ع الدنيا\nدنيا دنيا دنيا\nستاتها قلماظية ماتقولش مهلبية\nقبدا قبدا إيش جاب\nقربت أسيح قربت أسخسخ قربت أتكهرب الحق\nالحق الحق الحق\nسيبك م الفقهنة خالص من بكره هتبقى لابس بدل العمة كاسكيت","url":"https://fnanen.com/klmat/alaghany/s/syd-droysh/yashy5-8fa3h.html?arabic=%D9%8A%D8%A7%D8%B4%D9%8A%D8%AE%20%D9%82%D9%81%D8%A7%D8%B9%D9%87"}