{"title":"بعض الاوقات","author":"محمد بن عبدالعزيز","composer":"عزوف","date":"2021","lyrics":"بعض الاوقات احس انك قريب .. اقرب من اشتياقي للسهر\nوبعض الاوقات ما كنك حبيب حلم .. وابعد من حدود النظر\nادري انك قمر عيّا يغيب .. وانك ابعد كثير من القمر\nوادري اني بعد مالي نصيب .. فيك بس الامل فيني كبر\n\nشفت كيف اصبح احساسي غريب .. الوصل مر والفرقا امر\nبين ظني يخيب وما يخيب وبين .. احبك وما حبك قدر\nيا بخيل الشعور امرك عجيب .. وش يعز السحاب الا المطر\nكانك الحلم يا ليتك قريب .. وكانك الجرح يا قرب السهر","url":"https://fnanen.com/klmat/alaghany/a/a7lam/b3dh-alao8at.html?arabic=&#x628;&#x639;&#x636; &#x627;&#x644;&#x627;&#x648;&#x642;&#x627;&#x62A;"}