{"title":"كتاب المجروحين","lyricist":"سمير زكي","composer":"عصام كاريكا","date":"2019","lyrics":"إفتح كتاب المجروحين واقرا لي يا زماني\nهتلاقي أول سطر فيه مكتوب اسمي وعنواني\nوقولي كام جرح فيا وريني وما تخافش عليا\nمتعود علي ظلم الناس\nالأحزان واخد عليها بتونس في الوحدة فيها\nوأهي أيام بتفوت و خلاص\nوريني وما تخافش عليا\nمتعود علي ظلم الناس\n...\nإللي جرحوني وإللي فرحوني\nوإللي صبحوني بالدمع تلاقيهم\nمكتوبين في خانة يا زماني أمانة\nإقرأ وإوعى تنسي أي حد فيهم\nشكراً للي باعني و إللي زمان خدعني\nوإللي جه عليا قولوله بالسلامة\nعلشان يا زماني جرحني و بكاني\nمش هرجعله تاني لو قامت القيامة","url":"https://fnanen.com/klmat/alaghany/9/9abr-alrba3y/ktab-almjro7yn.html?arabic=%D9%83%D8%AA%D8%A7%D8%A8%20%D8%A7%D9%84%D9%85%D8%AC%D8%B1%D9%88%D8%AD%D9%8A%D9%86"}