{"title":"زليت","author":"محمد الخضيري","composer":"سمير مبروك","date":"1996","lyrics":"زليت وابن آدم معرض للخطا ..\nزليت وبحاله غضب جرحي سطا\nاستسمحك واقرا بعيونك لي عتب ..\nوش في يدي اعفيك عن هذا الغضب .. ليه العجب ؟\nانا بشر اخطي وسبحان اللي كامل بالعطا ..\nزليت ..\n\nقبل الوداع .. وآخر وداع ..\nاسمع كلامي وافهمه\nقبل الوداع .. وآخر وداع ..\nراجع سطور الناس بعمر الزمن\nمن فينا ما داس الخطا .. من فينا ؟؟\nمن فينا كامل بالعطا .. من فينا ؟؟\nانا بشر اخطي وسبحان اللي كامل بالعطا ..\nزليت ..\n\nاصبر علي ..\nاصبر علي .. وادمح خطاي\nاصبر علي ..\nاصبر علي .. وان ما قوى صبرك رضاي\nانا بهواي مجروح من يصبر علي\nهجرك الم .. اقولها واقسم قسم\nمثل الظفر .. يطلع يا عمري من اللحم\nانا بشر اخطي وسبحان اللي كامل بالعطا ..\nزليت ..","url":"https://fnanen.com/klmat/alaghany/5/5ald-3bdalr7mn/zlyt.html?arabic=%D8%B2%D9%84%D9%8A%D8%AA"}