{"title":"ابي باكر","lyrics":"ابي باكر عسى باكر يجي لقليبي الساهر\nيبدل كل اشجاني واعيش من العمر ثاني\nابي عمري اللي راح ابي انسى انا الجراح\nابي ضي القمر والليل تعبت وما بقى بي حيل\nتعبت وما بقى بي حيل\n\n\n\n\nابي عطره في صدري يفوح ابي يرد لي هالروح\nابيه العاشق المجنون صحيح إن الجنون فنون\nابيه يصير لي بسمه وفي ليل الهواء غنوه\nابي إحساسه ابي شعوره ابي اغوص في بحوره\nابي اغوص في بحوره\n\n\n كلمات:\n\n\n\n\n\n\n ألحان:\n\n\n\n\n\n\n تاريخ:\n\n\n\n\n\n\n\n\nاستمع إلى \"ابي باكر\" على أنغامي","author":"نهار","composer":"عبدالله القعود","date":"2021","url":"https://fnanen.com/klmat/alaghany/6/6lal-slamh/aby-bakr.html?arabic=ابي باكر"}