{"title":"حبر العيون","author":"يونس سلمان","composer":"نزار عبدالله","date":"2012","lyrics":"لغير الله ما اشكي الحال\nولو ابقى العمر مهموم\nابد مايفيد ضيق البال\nما دام ان الالم مقسوم\nوانا قلبي لزيم الخير\nوالاقي في الوفا دنياي\nاذا اعطي اكون بخير\nتعيش البسمه بين اشفاي\nغريبه حالتك يا انسان\nتزيد بقسوتك وتخون\nتجامل او تخاف فلان\nولا تخشى اله الكون\nبشر تظلم هنا وهناك\nوتبني فــي الخداع قصور\nوترمي في الـدروب أشـواك\nولا تدري الــزمان يدور","url":"https://fnanen.com/klmat/alaghany/r/rashd-almajd/7br-al3yon.html?arabic=%D8%AD%D8%A8%D8%B1%20%D8%A7%D9%84%D8%B9%D9%8A%D9%88%D9%86"}