{"title":"مبطلناش احساس","lyricist":"محمد القاياتي","composer":"محمد حمزه","date":"2020","lyrics":"كبرنا وعقلنا ما بقاش كلامهم يشغلنا\nولا بنهتم نعرف ناس بتهملنا\nكبرنا وفهمنا عرفنا ان الوجع اوقات\nبيجي ويمشي بس عشان يعلمنا\nبطلنا نقيس مقاماتنا بعيون الناس\nمش كل الناس بتشوف ولا كل الناس تتقاس\nبطلنا نحب زياده مبطلناش احساس\n\nسيبنا اللي بيسيبنا وبطل بعده يتعبنا\nبقينا مع اللي فاز بقلوبنا وكسبنا\nكبرنا في عينينا ودي الحاجه اللي تعنينا\nبقينا ندوس على الاوجاع تعلينا\nبطلنا نقيس مقاماتنا بعيون الناس\nمش كل الناس بتشوف ولا كل الناس تتقاس\nبطلنا نحب زياده مبطلناش احساس","url":"https://fnanen.com/klmat/alaghany/t/tamr-7sny/mb6lnash-a7sas.html?arabic=%D9%85%D8%A8%D8%B7%D9%84%D9%86%D8%A7%D8%B4%20%D8%A7%D8%AD%D8%B3%D8%A7%D8%B3"}