{"title":"كذاب","lyricist":"المعتصم","composer":"ثامر","date":"2012","lyrics":"لا عاد تحلف ما عاد اصدق\nالصادقه العين الصادق الموقف\n\nكذاب كذاب تجرحني ماتحسب\nكذاب كذاب بكل القصص تكذب\nلا عاد تحلف ما عاد اصدق\nالصادقه العين الصادق الموقف\n\nشفتك بعيني وقلبي تخون قصة حبي\nتبيع ليالي الشوق .. وتضحك وانا المحروق\nيكفي تدور وتلف .. تكذب علينا بحلف\nلا عاد تحلف ما عاد اصدق\nالصادقه العين الصادق الموقف\n\nما عاد اصدق حرف خذت القرار اوقف\nابعد كفاني هموم .. انا اقوى منك اليوم\nيكفي تدور وتلف .. تكذب علينا بحلف\nلا عاد تحلف ما عاد اصدق\nالصادقه العين الصادق الموقف","url":"https://fnanen.com/klmat/alaghany/th/thamr-altrky/kzaab.html?arabic=%D9%83%D8%B0%D8%A7%D8%A8"}