{"title":"بعد ايه","lyrics":"بـعــد إيــه أبكــي عليـه واشــتــاق إلــيـــــــه أنــــــــا\n\nحـــبـــــيـــــــتـــــــه لــــــيــــــه ضـــيــعـــتـــــه لــــــــيــــــــــه\n\nياما قالت لي عينيــــــــه ساعة الفراق خليـــك شــــويـــــة\n\nياما ندالي بدمعه للوداع واتـــــــرجــــــــــــى فـــــــيــــــا\n\nلــــيــــــه فـــــارقـــــتــــــه لـــيــــه لـــــيـــــه ضــــيــــعـــتـــــه لـــيــــــــه\n\nفــــــارقـتـه ليـه ...ضـــيـعـتـــه ليـــه ... حـبـيـتـــــــــه لـــــــيــــــــــــه ..؟\n\nقالـوا سمعنـــا حكـايـات الحبـايـب اللـي فارق واللـــــي خاصـم واللي غايــب\n\nواللـــي دارى حبـه حتـى عـن حبيبيـه واللـي قلبـه في عـذاب الحـب دايــــب\n\nبــس آه من اللي جرىلي عــمـره مـــا كـان يوم في بـــالي\n\nهـــــــو دا الحـــــــب اللي مــــاســمــعــتــــش عـــلـــيـــــــه\n\nيامــا قــالـت لي عينيـــه ساعـة الوداع خليـك شـــويــــــة\n\nياما ندالي بدمعه للوداع واتــــــرجـــــــى فـــــيــــــــــا\n\nيوم من عمري باهرب منه وابعد عنه وافضل وحدي لآخر عمــري مستنيــــك\n\nيوم من عمري هو اليوم اللي اتهنيت فيه واللي بكيت منه بكيت منـه عليـــك\n\nتقابلنا في الحياة عالود والحب الجميل وافترقنا كل واحد في طريق خالي طـويل\n\nحــــتـــــى مــــــا عـــــــرفــــتـــــش ســــــاعــــتـــهــــــا وقـــــلـــــــــت\n\nيـا مـا قـالـت لي عيـنيه ســاعــة الفـراق خــليـك شــوية\n\nيا ما نادالي بدمعه للوداع واتـــــرجـــــــــى فــــيــــــــــــا\n\nلـيــه فـــارقــتـــه لـــيــه لــيـــه ضـيـعــتــه لــيــه حــبــيــتــه لـيه لـيـه ليـــه","author":"مأمون الشناوي","composer":"كمال الطويل","date":"1961","url":"https://fnanen.com/klmat/alaghany/3/3bdal7lym-7afzh/b3d-ayh.html?arabic=بعد ايه"}