{"title":"يا كريم","lyricist":"بدر بن عبدالمحسن","composer":"سراج عمر","lyrics":"يا كريم .. يا كريم ..\nنوض برق .. وريح ديم ..\nوفي الحشا .. رمل قديم ..\nلاح برق في الظلام .. شقق الظلما سناه ..\nيا هلا بغيث الغمام .. وياهلا بعشب الحياة ..\nلاح برق في العتيم ..\nيا كريم ..\n\nسدرة الوادي العتيق .. وسط صدري اغصونها ..\nعندها وعد وطريق .. وحالف ماخونها ..\nلاح برق في العتيم ..\nيا كريم ..\n\nلاح برق في الدجا .. نقض جروح التراب ..\nنزرع الأرض برجا .. جود خلاق السحاب ..\nلاح برق في العتيم ..\nيا كريم ..","url":"https://fnanen.com/klmat/alaghany/6/6lal-mda7/ya-krym.html?arabic=%D9%8A%D8%A7%20%D9%83%D8%B1%D9%8A%D9%85"}