{"title":"احلى دنيا","lyrics":"احترت اشكي ولا احكي ولا ابكي من فرحتي\n\nمن شوقي ليك يا حبيبي بدعي تكون في يوم من إسمتي\n\nيا احلى دنيا عشتها في الكون بحاله\n\nفي عنيك ليالي عشقتها أول ما مالو\n\nكلمة يا عمري قلتها لحظة لقانا\n\nماعرفش قلبي لما شافك ايه جراله\nطول عمري خايفة احب واعشق زي كل الناس\n\nلإني ماملكش في حياتي غير حبة الإحساس\n\nشفتك ملكت كل شيء فيّا بثواني\n\nعلمت قلبي ازاي يحب ويعرف الاخلاص\nاحتارت اشكي ولا احكي ولا ابكي من فرحتي\n\nمن شوقي ليك يا حبيبي بدعي تكون في يوم من إسمتي\n\n \n\n\n كلمات:\n\n\n\n\n\n\n ألحان:\n\n\n\n\n\n\n تاريخ:\n\n\n\n\n\n\n\n\nاستمع إلى \"احلى دنيا\" على أنغامي","author":"محمد رفاعي","composer":"محمد رفاعي","date":"2005","url":"https://fnanen.com/klmat/alaghany/a/alysa/a7la-dnya.html?arabic=احلى دنيا"}