{"title":"اصدق ما كتبت","lyrics":"انتِ تدرين من انتِ\n\nتدرين انك غديتي كل شي\n\nوانك غديتي شمس ليلي وفي الهجير الفي\n\nوانك اصدق ماكتبت .. وانك اصدق ما كذبت\n\nوانك احزني وفرحي .. لى ضحكت او انجرحت\n\nوانك غديتي ياعذابي اغلى من حبي علي\n\n\n\nقبل احبك .. ياما كذبني القصيد\n\nوبعد حبك .. صار يكتبني القصيد\n\nهويوصفك بسمه وطرف\n\nوانا اعشقك في كل حرف\n\nمنك شكا لي وصف حسنك اتعبه ..\n\nوانا شكيتك عشقي لحبك اعجبه ..\n\nمهما شكا ومهما وصف\n\nانتِ احلى ماكتبت .. وانتِ اصدق ماكذبت\n\nوانتِ احساسي وجرحي لى ضحكت او انجرحت\n\nوانتِ غديتي ياعذابي اغلى من حبك علي\n\n\n كلمات:\n\n\n\n\n\n\n ألحان:\n\n\n\n\n\n\n تاريخ:","author":"عبدالرحمن بن مساعد","composer":"عبادي الجوهر","date":"1988","url":"https://fnanen.com/klmat/alaghany/3/3bady-aljohr/a9d8-ma-ktbt.html?arabic=اصدق ما كتبت"}