{"title":"انا وياك","lyricist":"كونسويلو فيلاسكيز","composer":"كونسويلو فيلاسكيز","date":"2017","lyrics":"حبيبي .. حبيبي بحبك غنيي حزينه منسيه شو بتشبهك\nحبيبي .. حبيبي بحبك قصتنا غنيي بغنيها انا وياك\nمن اول ما التقينا كل ما زعلنا واتراضينا ع طول كنت تغنيلي ياها\nايامنا وليالينا وحكايتنا وماضينا كيف بتفكر انه ممكن انساك\nحبينا وكنا صغار مشينا سوا المشوار غنيتنا كانت هي البدايه\nمثل الحب رافقتنا كل ما بعدنا قربتنا هاي قصتنا وما الها نهايه\nحبيبي .. حبيبي بحبك غنيي حزينه منسيه شو بتشبهك\nBesame Mucho قصتنا غنيي بغنيها انا وياك","url":"https://fnanen.com/klmat/alaghany/f/fyroz/ana-oyak.html?arabic=%D8%A7%D9%86%D8%A7%20%D9%88%D9%8A%D8%A7%D9%83"}