{"title":"هيك مشق الزعروره","author":"الأخوين رحباني","composer":"الأخوين رحباني","date":"1996","lyrics":"بالضيعة ياللي عاشقة النجمات\nيسهروا بظل الهوى سهرات\nوبيرقصوا رقصة بحبها كتير حبا كتير\nعاغنا الحلوين والحلوات\nهيك مشق الزعرورة يا يما هيك\nهيك بتمشي الأمورة يا يما هيك\nهيك مشق الزعرورة يا يما هيك\nوهيك بتغني العصفورة يا يما هيك\nنحنا بعليي خضرا عملنا سهرة\nعجناح النسمة وعطرا أتشوقنا اليك\nهيك مشق الزعرورة يا يما هيك\nهيك الحلوة وزهورا بيميلوا هيك\nوالحب اللي منتهي بليل غنانيك\nعم تسألنا لياليه وتغمزنا عينيك\nهيك مشق الزعرورة يا يما هيك\nهيك الأحلام قصورة تتعمر هيك","url":"https://fnanen.com/klmat/alaghany/f/fyroz/hyk-msh8-alz3rorh.html?arabic=%D9%87%D9%8A%D9%83%20%D9%85%D8%B4%D9%82%20%D8%A7%D9%84%D8%B2%D8%B9%D8%B1%D9%88%D8%B1%D9%87"}