{"title":"ليلة وداعنا","author":"مصطفى زكي","composer":"امجد العطافي","date":"2006","lyrics":"يا حبيبي  ...\nكان احلى ليلة في عمرنا .. ليلة وداعنا لبعضنا\nلما احنا حسينا الوداع .. ح ياخذنا لسنين الضياع ..\nسلمتلك .. سلمتلي .. وناديت عليك وندهتلي\nوكاني لسه ما بين ايديك .. وانت بحنانك ملت لي\n\nحسيت حبيبي اني حضيع من غير عينيك\nلما بثواني لقيتني مش بلمس ايديك\nمديت ايديا حضنت ايديك\nوالدموع رجعت عبيدك ورجعت اكون من تاني عيدك\nوانت اللي من نظرة عينيى رجعتلي ..\nسلمتلك .. سلمتلي .. وناديت عليك وندهتلي\nوكاني لسه ما بين ايديك .. وانت بحنانك ملت لي\n\nحنيت يا عمري لكل لحظة عشتها\nولكل كلمة منك انت سمعتها\nنسيت الالمي كلها\nوالدموع رجعت عبيدك ورجعت اكون من تاني عيدك\nوانت اللي من نظرة عينيى رجعتلي ..\nسلمتلك .. سلمتلي .. وناديت عليك وندهتلي\nوكاني لسه ما بين ايديك .. وانت بحنانك ملت لي","url":"https://fnanen.com/klmat/alaghany/j/jorj-osof/lylt-oda3na.html?arabic=%D9%84%D9%8A%D9%84%D8%A9%20%D9%88%D8%AF%D8%A7%D8%B9%D9%86%D8%A7"}