{"title":"الحلوه والمره","author":"كاظم السعدي","composer":"وليد الشامي","date":"2009","lyrics":"يخون الحلوه والمره ويخلني على جمره\nعجيبه شلون يتبرى ويضيع عمري وسنيني\nعجيبه شلون يتخلى يخون صويحبه وخله\nرحمه بقلبه ما خلى كفـآيا دموعي ياعيني\n\nاذا يسوى الدمع نسيني وخل ينهدم حيلي\nاصيح الويل ياويلي ولا واحد يواسيني\nانا صابر على همي اذوب ويحترق دمي\nبعد شو تدريد ياعمري تبي ميت تخليني\n\nانا اسف على حبك لان مثل الحجر قلبك\nسكن بقليبي وتربى وكبر وقطع شرايني\nحنين وعلتي عله وانا قلبي القهر سله\nيا طاير طير وقله ترى غرقه بساتيني","url":"https://fnanen.com/klmat/alaghany/a/alosmy/al7loh-oalmrh.html?arabic=&#x627;&#x644;&#x62D;&#x644;&#x648;&#x647; &#x648;&#x627;&#x644;&#x645;&#x631;&#x647;"}