{"title":"انت انا","lyrics":"أنـت أنـا دائمـا هنــا فـي عنينـا\n\nوفـي قلبـي أنـا .. أنـا\n\nدائمـا قريـب ولا يــوم تغـيـب ولا يخلـص الشــوق مننـا\n\nأروح بـلاد وأشـوف وجـوه وساعـات أضيـع وكتيـر بتـوه\n\nلكـن بعــود مـن تانـي ليـك ألاقـي روحـي معـاك وبيـك\n\nمـا أنــت أنــا\nكـام مـره شوفتـك فـي السحــاب\n\nفـي بـلاد غريبــه عننــا\n\nزي القمـر وسـط الظــلام يطلــع ويبـرق حبنـــا\n\nويـا دوب راح أبــدا بالســلام\n\nأتارينــي بحلـم بيـك أنـا يغلــب شفايفــي الابتســام\n\nعلــى اللـي جرالــي فـي بعدنــا\n\nوأتاريــك بعيــد بعيـد وأملـي الوحيـد وحيد\n\nدايـر على فـصول السنـه\nومـره كنـا زعـلانين متفرقـين عـن بعضنـا\n\nوسهـرت ويـا السهرانـين بتمنـى أعيـش لحظـة هنـا\n\nشفتــك فـي كـل الموجوديـن بتبـص فـي عنينا أنـا\n\nجـيت ألمسـك لمـس الإيديـن لقـيت فـراغ بيضمنـا\n\nورجعـت ليـك ليـك أسـأل عليـك عليـك\n\nورجعلنـا تانـي لحبنـــا\n\n\n\n\nعمر بطيشه\n\n\n\n\n\n\nمحمد سلطان\n\n\n\n\n\n\n1987","author":"عمر بطيشه","composer":"محمد سلطان","date":"1987","url":"https://fnanen.com/klmat/alaghany/s/smyrt-s3yd/ant-ana.html?arabic=انت انا"}