{"title":"انا والشوق","lyrics":"أنا والشوق يطول ليلي وانت تغيب\n\nأنا والعين نسأل فين أغلى حبيب\n\nأنا قلبي ينادي ليك وروحي تروح ليك\n\nيوقف بي الزمان واستنى شوف عينيك\n\nأنا قلبي ينادي ليك وروحي تروح ليك\n\nيوقف بي الزمان واستنى شوف عينيك\n\n\nارجعلي أشوفك والقلب يرتاح\n\nريحني ياحبيبي من نار الاشواق\n\nتلقاك في البسمة عيوني وتغني الافراح\n\nوالقاك ياحبيبي زي أنا مشتاق\n\nأوبارينا رينا اوباري نارا اناري نارينا رينا رينارا\n\n\nأنا في البعد ماتعرف عيوني النوم\n\nولا يومين ولا شهرين ولا ميت يوم\n\nأنا قلبي ينادي ليك وروحي تروح ليك\n\nيوقف بي الزمان واستنى شوف عينيك\n\nأنا قلبي ينادي ليك وروحي تروح ليك\n\nيوقف بي الزمان واستنى شوف عينيك\n\n\nارجعلي أشوفك والقلب يرتاح\n\nريحني ياحبيبي من نار الاشواق\n\nتلقاك في البسمة عيوني وتغني الافراح\n\nوالقاك ياحبيبي زي أنا مشتاق\n\nأوبارينا رينا اوباري نارا اناري نارينا رينا رينارا\n\n \n\n\n \n\n\n\n\nطوني ابي كرم\n\n\n\n\n\n\nبودي نعوم","author":"طوني ابي كرم","composer":"بودي نعوم","url":"https://fnanen.com/klmat/alaghany/m/myryam-fars/ana-oalsho8.html?arabic=انا والشوق"}