{"title":"تراعيني قيراط","author":"حسين السيد","composer":"محمد عبدالوهاب","date":"1953","lyrics":"تراعينى قيراط أراعيك قيراطين\nو تشــوفنى بعين أشــــوفك باتنين\nإنت اللى بديت بجفاك و أســـــــاك\nو إنت اللى نسيت عشرتى و ياك\nعمرك ما رعيت قلبى  اللى رعاك\nخليتنى هربت على قد هواك\nو تراعينى  قيراط....\nقــلبى فى إيديك و إزاى تجافيه\nمجروح بعينيك و الجرح كداويه\nياما حــن إليك و لا حسيت\nو لا هانش عليك يوم تسأل فيه\nو تراعينى قيراط....\nياهنا  اللى معاه أحباب يراعوه\nإن قال يوم  آه يا بالروح يداووه\nو اللي  انا بـــهواه الناس شغلوه\nلا أنا طلت هواه و لا هم طالوه\nو تراعينى قيراط....","url":"https://fnanen.com/klmat/alaghany/m/m7md-3bdalohab/tra3yny-8yra6.html?arabic=%D8%AA%D8%B1%D8%A7%D8%B9%D9%8A%D9%86%D9%8A%20%D9%82%D9%8A%D8%B1%D8%A7%D8%B7"}