{"title":"يا وابور قول لي","lyricist":"احمد رامي","composer":"محمد عبد الوهاب","date":"1938","lyrics":"يا وابور قول لي رايح على فين\nيا وابور قول لي وسافرت منين\nيا وابور قول لي\n\nعمال تجري قبلي وبحري\nتنزل وادي تطلع كوبري\nحوِد مره وبعدين دُغري\nما تقول يا وابور رايح على فين\nصوتك يدوي وانت بتهوي\nوالبعد أليم ناره تكوي\nوالارض بساط وانت بتطوي\nما تقول يا وابور رايح على فين\n\nيا وابور قول لي رايح على فين\nيا وابور قول لي وسافرت منين\nيا وابور قول لي\n\nقربت غريب وبعدت قريب\nوجمعت حبيب على شمل حبيب\nوالقرب نصيب والبعد نصيب\nما تقول يا وابور رايح علي فين\nإن طال الوقت على الركاب\nيجري كلامهم في سؤال وجواب\nبعد شوية يبقوا احباب\nوده يعرف ده رايح على فين\n\nأنا رحت معاك ورجعت معاك\nوأنا إيه كان مقسوم لي وياك\nدي كانت نظره من هنا لهناك\nالعين عرفت رايحين علي فين\nيا وابور","url":"https://fnanen.com/klmat/alaghany/m/m7md-3bdalohab/ya-oabor-8ol-ly.html?arabic=%D9%8A%D8%A7%20%D9%88%D8%A7%D8%A8%D9%88%D8%B1%20%D9%82%D9%88%D9%84%20%D9%84%D9%8A"}